config_injector/__init__.py
config_injector/config.py
config_injector/exc.py
config_injector/injector.py
config_injector/utils.py
config_injector-0.3.1.dist-info/LICENSE
config_injector-0.3.1.dist-info/WHEEL
config_injector-0.3.1.dist-info/METADATA
config_injector-0.3.1.dist-info/RECORD
