Metadata-Version: 2.1
Name: config-injector
Version: 0.3.1
Summary: Simple dependency injection framework for python for easy and logical app configuration.
Home-page: https://github.com/DustinMoriarty/config-injector
License: MIT
Author: DustinMoriarty
Author-email: dustin.moriarty@protonmail.com
Requires-Python: >=3.6,<4.0
Classifier: License :: OSI Approved :: MIT License
Classifier: Programming Language :: Python :: 3
Classifier: Programming Language :: Python :: 3.6
Classifier: Programming Language :: Python :: 3.7
Classifier: Programming Language :: Python :: 3.8
Classifier: Programming Language :: Python :: 3.9
Requires-Dist: PyYAML (>=5.3.1,<6.0.0)
Requires-Dist: importlib-metadata (>=0.12,<=4); python_version < "3.8"
Requires-Dist: pyaml (>=20.4.0,<21.0.0)
Requires-Dist: toml (>=0.10.2,<0.11.0)
Project-URL: Documentation, https://github.com/DustinMoriarty/config-injector
Project-URL: Repository, https://github.com/DustinMoriarty/config-injector
